litter_getter/__init__.py
litter_getter/hero.py
litter_getter/pubmed.py
litter_getter/ris.py
litter_getter/utils.py
litter_getter-0.3.0.dist-info/LICENSE
litter_getter-0.3.0.dist-info/METADATA
litter_getter-0.3.0.dist-info/WHEEL
litter_getter-0.3.0.dist-info/top_level.txt
litter_getter-0.3.0.dist-info/RECORD
