Metadata-Version: 2.1
Name: litter-getter
Version: 0.3.0
Summary: Retrieve literature from biomedical reference libraries such as PubMed, EPA's HERO, and imports from Endnote RIS exports
Home-page: https://github.com/shapiromatron/litter_getter
Author: Andy Shapiro
Author-email: shapiromatron@gmail.com
License: MIT license
Keywords: litter_getter
Platform: UNKNOWN
Classifier: Intended Audience :: Developers
Classifier: License :: OSI Approved :: MIT License
Classifier: Natural Language :: English
Classifier: Programming Language :: Python :: 3
Classifier: Programming Language :: Python :: 3.6
Requires-Dist: requests
Requires-Dist: XlsxWriter
Requires-Dist: RISparser
Provides-Extra: dev
Requires-Dist: wheel ; extra == 'dev'
Requires-Dist: black (==19.10b0) ; extra == 'dev'
Requires-Dist: flake8 (==3.7.9) ; extra == 'dev'
Requires-Dist: isort (==4.3.21) ; extra == 'dev'
Requires-Dist: flake8-isort (==2.8.0) ; extra == 'dev'
Requires-Dist: twine ; extra == 'dev'
Provides-Extra: test
Requires-Dist: pytest ; extra == 'test'
